setup.py
orangepay/__init__.py
orangepay/client.py
orangepay_client.egg-info/PKG-INFO
orangepay_client.egg-info/SOURCES.txt
orangepay_client.egg-info/dependency_links.txt
orangepay_client.egg-info/not-zip-safe
orangepay_client.egg-info/top_level.txt