Metadata-Version: 1.1
Name: orangepay-client
Version: 0.1.0
Summary: Library to work with payments processor OrangePay
Home-page: https://github.com/smartfin/orangepay_client
Author: Serhiy Martynenko
Author-email: serhiy.martynenko@gmail.com
License: BSD
Platform: UNKNOWN
Classifier: Development Status :: 3 - Alpha
Classifier: Environment :: Web Environment
Classifier: Intended Audience :: Developers
Classifier: License :: OSI Approved :: BSD License
Classifier: Operating System :: OS Independent
Classifier: Programming Language :: Python
Classifier: Framework :: Django
